ambhas/__init__.py
ambhas/ai.py
ambhas/dielectric.py
ambhas/dubois.py
ambhas/errlib.py
ambhas/krige.py
ambhas/richards.py
ambhas/stats.py
ambhas-1.1.0.dist-info/LICENSE
ambhas-1.1.0.dist-info/METADATA
ambhas-1.1.0.dist-info/WHEEL
ambhas-1.1.0.dist-info/top_level.txt
ambhas-1.1.0.dist-info/RECORD
