Metadata-Version: 2.1
Name: ambhas
Version: 1.1.0
Summary: A library for data science in water
Author-email: Sat Kumar Tomer <satkumartomer@gmail.com>
Project-URL: Homepage, https://github.com/tomersk/ambhas
Project-URL: Bug Tracker, https://github.com/tomersk/ambhas/issues
Classifier: Programming Language :: Python :: 3
Classifier: License :: OSI Approved :: GNU Library or Lesser General Public License (LGPL)
Classifier: Operating System :: OS Independent
Classifier: Topic :: Scientific/Engineering
Classifier: Development Status :: 4 - Beta
Classifier: Intended Audience :: Science/Research
Requires-Python: >=3.7
License-File: LICENSE
